simpleutils_azan/__init__.py
simpleutils_azan/math_utils.py
simpleutils_azan/setup.py
simpleutils_azan/string_utils.py
simpleutils_azan_ids-0.1.1.dist-info/METADATA
simpleutils_azan_ids-0.1.1.dist-info/WHEEL
simpleutils_azan_ids-0.1.1.dist-info/top_level.txt
simpleutils_azan_ids-0.1.1.dist-info/RECORD
