Metadata-Version: 2.4
Name: simpleutils_azan-ids
Version: 0.1.1
Summary: A simple utility library for math and string operations
Author: Azan
Author-email: f2022332047@umt.edu.pk
Requires-Python: >=3.6
Dynamic: author
Dynamic: author-email
Dynamic: requires-python
Dynamic: summary
